filter.py
ipng.py
ipng-0.0.5.dist-info/LICENSE
ipng-0.0.5.dist-info/METADATA
ipng-0.0.5.dist-info/WHEEL
ipng-0.0.5.dist-info/top_level.txt
ipng-0.0.5.dist-info/RECORD
