Metadata-Version: 2.1
Name: ipng
Version: 0.0.5
Summary: Intuitive PNG library.
Home-page: https://github.com/hanjoes/ipng
Author: hanjoes
Author-email: hanzhou87@gmail.com
License: UNKNOWN
Platform: UNKNOWN
Classifier: Programming Language :: Python :: 3
Classifier: License :: OSI Approved :: MIT License
Classifier: Operating System :: OS Independent
